README.md
setup.cfg
setup.py
traintorch/TrainTorch.py
traintorch/__init__.py
traintorch.egg-info/PKG-INFO
traintorch.egg-info/SOURCES.txt
traintorch.egg-info/dependency_links.txt
traintorch.egg-info/requires.txt
traintorch.egg-info/top_level.txt