Metadata-Version: 2.1
Name: traintorch
Version: 1.0.1
Summary: Package for live visualization of metrics during training of a machine learning model
Home-page: https://github.com/rouzbeh-afrasiabi/traintorch
Author: Rouzbeh Afrasiabi
Author-email: rouzbeh.afrasiabi@gmail.com
License: UNKNOWN
Download-URL: https://github.com/rouzbeh-afrasiabi/traintorch/archive/1.0.1-alpha.1.tar.gz
Keywords: training,visualization,loss,plot,live,jupyter notebook,matplotlib
Platform: UNKNOWN
Classifier: Programming Language :: Python :: 3.6
Classifier: License :: OSI Approved :: MIT License
Classifier: Operating System :: OS Independent
